tahutils/__init__.py
tahutils/parse.py
tahutils/spb.py
tahutils/tahu/__init__.py
tahutils/tahu/array_packer.py
tahutils/tahu/host_session_establishment.py
tahutils/tahu/readme.md
tahutils/tahu/sparkplug_b.py
tahutils/tahu/sparkplug_b_pb2.py
tahutils/tahu_version.txt
tahutils/types.py
tahutils/utils.py
tahutils-0.1.11.dist-info/LICENSE.txt
tahutils-0.1.11.dist-info/METADATA
tahutils-0.1.11.dist-info/WHEEL
tahutils-0.1.11.dist-info/RECORD
