Metadata-Version: 2.1
Name: tahutils
Version: 0.1.11
Summary: Python utilities for Tahu & Sparkplug B.
Author: Justin Dula
Author-email: justin.dula@intellicintegration.com
Requires-Python: >=3.10,<4.0
Classifier: License :: OSI Approved :: Eclipse Public License 2.0 (EPL-2.0)
Classifier: Operating System :: OS Independent
Classifier: Programming Language :: Python :: 3
Classifier: Programming Language :: Python :: 3.10
Classifier: Programming Language :: Python :: 3.11
Classifier: Programming Language :: Python :: 3.12
Requires-Dist: protobuf (>=3.20.0,<5.0.0)
Project-URL: Homepage, https://github.com/intellicintegration/TahUtils
Project-URL: Issues, https://github.com/intellicintegration/TahUtils/issues
